zucker/__init__.py
zucker/exceptions.py
zucker/utils.py
zucker/client/__init__.py
zucker/client/aiohttp.py
zucker/client/base.py
zucker/client/requests.py
zucker/codegen/__init__.py
zucker/codegen/__main__.py
zucker/codegen/inspection.py
zucker/codegen/interactive/__init__.py
zucker/codegen/interactive/inspect.py
zucker/filtering/__init__.py
zucker/filtering/basic.py
zucker/filtering/combining.py
zucker/filtering/types.py
zucker/model/__init__.py
zucker/model/module.py
zucker/model/view.py
zucker/model/fields/__init__.py
zucker/model/fields/base.py
zucker/model/fields/relationships.py
zucker/model/fields/scalars.py
zucker-0.2.7.dist-info/LICENSE
zucker-0.2.7.dist-info/METADATA
zucker-0.2.7.dist-info/WHEEL
zucker-0.2.7.dist-info/top_level.txt
zucker-0.2.7.dist-info/RECORD
