Metadata-Version: 2.1
Name: zucker
Version: 0.2.7
Summary: A straightforward, Pythonic interface for the SugarCRM API
Home-page: https://github.com/iWeltAG/zucker
Author: iWelt AG
License: UNKNOWN
Project-URL: Bug Tracker, https://github.com/iWeltAG/zucker/issues
Platform: UNKNOWN
Classifier: Programming Language :: Python :: 3
Classifier: License :: OSI Approved :: MIT License
Classifier: Operating System :: OS Independent
Requires-Python: >=3.7
License-File: LICENSE
